getsitemap/__init__.py
getsitemap/retrieve_sitemap.py
getsitemap-0.1.5.dist-info/LICENSE.md
getsitemap-0.1.5.dist-info/METADATA
getsitemap-0.1.5.dist-info/WHEEL
getsitemap-0.1.5.dist-info/top_level.txt
getsitemap-0.1.5.dist-info/RECORD
