Metadata-Version: 2.1
Name: getsitemap
Version: 0.1.5
Summary: Retrieve all URLs from a sitemap.
Home-page: https://github.com/capjamesg/getsitemap
Author: capjamesg
Author-email: jamesg@jamesg.blog
Classifier: Programming Language :: Python :: 3
Classifier: License :: OSI Approved :: MIT License
Classifier: Operating System :: OS Independent
Requires-Python: >=3.7
License-File: LICENSE.md
Requires-Dist: requests
Requires-Dist: beautifulsoup4
Provides-Extra: dev
Requires-Dist: flake8 ; extra == 'dev'
Requires-Dist: black ==22.3.0 ; extra == 'dev'
Requires-Dist: isort ; extra == 'dev'
Requires-Dist: twine ; extra == 'dev'
Requires-Dist: pytest ; extra == 'dev'
Requires-Dist: wheel ; extra == 'dev'
